nessai_bilby/__init__.py
nessai_bilby/model.py
nessai_bilby/plugin.py
nessai_bilby-0.2.1.dist-info/licenses/LICENSE
nessai_bilby-0.2.1.dist-info/METADATA
nessai_bilby-0.2.1.dist-info/WHEEL
nessai_bilby-0.2.1.dist-info/entry_points.txt
nessai_bilby-0.2.1.dist-info/top_level.txt
nessai_bilby-0.2.1.dist-info/RECORD
