Metadata-Version: 2.4
Name: nessai-bilby
Version: 0.2.1
Summary: Interface and plugin for using nessai in bilby
Author-email: "Michael J. Williams" <michaeljw1@googlemail.com>
License: MIT
Classifier: Programming Language :: Python :: 3
Requires-Python: >=3.9
License-File: LICENSE
Requires-Dist: bilby>=2.3.0
Requires-Dist: nessai
Requires-Dist: numpy
Requires-Dist: pandas
Requires-Dist: scipy
Provides-Extra: test
Requires-Dist: pytest; extra == "test"
Dynamic: license-file
